LICENSE
README.md
__init__.py
setup.py
ssdata.py
ssdata_datasource.py
ssdata_util.py
ss_datafeed.egg-info/PKG-INFO
ss_datafeed.egg-info/SOURCES.txt
ss_datafeed.egg-info/dependency_links.txt
ss_datafeed.egg-info/top_level.txt