Metadata-Version: 2.1
Name: ss-datafeed
Version: 1.0.7
Summary: ss datafeed from ningbo
Home-page: http://www.sumscope.com
Author: kongshanxuelin
Author-email: 33666490@qq.com
License-File: LICENSE
